<?xml version="1.0" encoding="UTF-8" standalone="yes"?>

<item>
<title>tve1</title>
<thumbnail></thumbnail>
<fanart></fanart>
<link>http://xc.cobra-iptv.com:25461/live/belgium-v2/Uxf2oTL0bW/795.ts</link>
<externallink></externallink>
</item>

<item>
<title>lista españa</title>
<thumbnail></thumbnail>
<fanart></fanart>
<link>http://ignoreme</link>
<externallink>http://212.178.96.210:3130/playlist.m3u8</externallink>
</item>

<item>
<title>1 españa</title>
<thumbnail></thumbnail>
<fanart></fanart>
<link>http://xc.cobra-iptv.com:25461/live/belgium-v2/Uxf2oTL0bW/793.ts</link>
<externallink></externallink>
</item>