<?xml version="1.0" encoding="UTF-8" standalone="yes"?>

<item>
<title>[COLOR yellow][COLOR red]NARCOS[/COLOR]</title>
<thumbnail>http://ayayay.tv/wp-content/uploads/2015/10/narcos.jpg</thumbnail>
<fanart>http://www.queveoennetflix.com/wp-content/uploads/2015/10/narcos-larga.png</fanart>
<link>ignoreme</link>
<externallink>https://raw.githubusercontent.com/elchocolate/tvchocotv/master/NARCOS.xml</externallink>
</item>

<item>
<title>[COLOR yellow]JUEGO[/COLOR] [COLOR white]DE[/COLOR] [COLOR red]TRONOS[/COLOR]</title>
<thumbnail>https://cdn2.areajugones.es/wp-content/uploads/2017/03/juego-de-tronos.png</thumbnail>
<fanart>https://i.imgur.com/TFXFy6z.png</fanart>
<link>ignoreme</link>
<externallink>https://raw.githubusercontent.com/elchocolate/tvchocotv/master/series/juego%20de%20tronos.xml</externallink>
</item>

<item>
<title> [COLOR yellow]7[/COLOR] [COLOR white]VI[/COLOR][COLOR red]VIDAS[/COLOR] </title>
<thumbnail>http://www.elnortedecastilla.es/multimedia/201501/29/media/010-gal-amparo-baro.jpg</thumbnail>
<fanart></fanart>
<link>ignoreme</link>
<externallink>https://raw.githubusercontent.com/elchocolate/tvchocotv/master/series/7Vidas.xml</externallink>
</item>

<item>
<title>  </title>
<urlsolve></urlsolve>
<thumbnail></thumbnail>
<fanart></fanart>
<link>ignoreme</link>
<externallink></externallink>
</item>

<item>
<title>  </title>
<urlsolve></urlsolve>
<thumbnail></thumbnail>
<fanart></fanart>
<link>ignoreme</link>
<externallink></externallink>
</item>

<item>
<title>  </title>
<urlsolve></urlsolve>
<thumbnail></thumbnail>
<fanart></fanart>
<link>ignoreme</link>
<externallink></externallink>
</item>

<item>
<title>  </title>
<urlsolve></urlsolve>
<thumbnail></thumbnail>
<fanart></fanart>
<link>ignoreme</link>
<externallink></externallink>
</item>

<item>
<title>  </title>
<urlsolve></urlsolve>
<thumbnail></thumbnail>
<fanart></fanart>
<link>ignoreme</link>
<externallink></externallink>
</item>

<item>
<title>  </title>
<urlsolve></urlsolve>
<thumbnail></thumbnail>
<fanart></fanart>
<link>ignoreme</link>
<externallink></externallink>
</item>